notpotty/__init__.py
notpotty/core.py
notpotty/utils.py
notpotty/words.py
notpotty-0.1.1.dist-info/METADATA
notpotty-0.1.1.dist-info/WHEEL
notpotty-0.1.1.dist-info/RECORD
