Metadata-Version: 2.3
Name: notpotty
Version: 0.1.1
Summary: Фильтр нецензурной лексики для русского языка
License: MIT
Keywords: mat,censor,russian
Author: StreetShiffter
Author-email: agwzdushaz@gmail.com
Requires-Python: >=3.8,<4.0
Classifier: License :: OSI Approved :: MIT License
Classifier: Programming Language :: Python :: 3
Classifier: Programming Language :: Python :: 3.8
Classifier: Programming Language :: Python :: 3.9
Classifier: Programming Language :: Python :: 3.10
Classifier: Programming Language :: Python :: 3.11
Classifier: Programming Language :: Python :: 3.12
Classifier: Programming Language :: Python :: 3.13
Project-URL: Repository, https://github.com/StreetShiffter/notpotty
